3x8Decoder/decoder3_8.v
// Q1. Write a RTL coe for 3:8 decoder using Behavioral abstraction and to
// verify the same
//

module decoder3_8 (Y, A,en);
       output reg [7:0] Y;
       input [2:0] A;
       input en;

       always@ (*) begin
	       if(en)
	       begin
		       case (A)
			       3'b000 : Y = 8'd0;
			       3'b001 : Y = 8'd1;
			       3'b010 : Y = 8'd2;
			       3'b011 : Y = 8'd3;
			       3'b100 : Y = 8'd4;
			       3'b101 : Y = 8'd5;
			       3'b110 : Y = 8'd6;
			       3'b111 : Y = 8'd7;
			       default : Y = 8'd0;
		       endcase
 
	       end
	       else begin
		       Y = 8'dz;
	       end


       end


endmodule

3x8Decoder/decoder3_8_tb.v
// Q1. Write a testbench to verify 3:8 decoder


module decoder3_8_tb();
       wire [7:0] Y;
       reg [2:0] A;
       reg en;

       decoder3_8 dut (
	       .Y(Y),
	       .A(A),
	       .en(en)
       );

       task initial_c;
	   begin 
	   A = 3'b000;
	   en = 1'b0;
	   #5;
	   $display($time, "inputs:--- A=%b , en=%b , output:--- Y=%b ", A,en,Y);
   end
   endtask

   task stimuli(input [2:0] a, input enable);
	   begin
		   A = a;
		   en = enable;
		   #5;
		   $display($time, "inputs:-- A=%b , en=%b , output:--- Y=%b", A,en,Y);
	   end
   endtask

   initial 
   begin
	   $display("----- 3:8 Decoder using Behavioral abstraction-----");
	   $dumpfile("dump.vcd");
	   $dumpvars(0,decoder3_8_tb);

	   initial_c;

	   // Cases when en = 0
	   stimuli(3'b000 , 1'b0); #5;
	   stimuli(3'b001 , 1'b0); #5;
	   stimuli(3'b111 , 1'b0); #5;
		#5;
	   //Cases when en = 1
	   stimuli(3'b000 , 1'b1); #5;
	   stimuli(3'b001 , 1'b1); #5;
	   stimuli(3'b010 , 1'b1); #5;
	   stimuli(3'b011 , 1'b1); #5;
	   stimuli(3'b100 , 1'b1); #5;
	   stimuli(3'b101 , 1'b1); #5;
	   stimuli(3'b110 , 1'b1); #5;
	   stimuli(3'b111 , 1'b1); #5;
	   

	   $monitor($time,"inputs:--- A=%b , en=%b , outputs:--- Y=%b", A,en,Y);

	   $finish;

   end


endmodule

3x8Decoder/dump.vcd
$date
	Wed Sep 24 22:26:12 2025
$end
$version
	Icarus Verilog
$end
$timescale
	1s
$end
$scope module decoder3_8_tb $end
$var wire 8 ! Y [7:0] $end
$var reg 3 " A [2:0] $end
$var reg 1 # en $end
$scope module dut $end
$var wire 3 $ A [2:0] $end
$var wire 1 # en $end
$var reg 8 % Y [7:0] $end
$upscope $end
$scope task initial_c $end
$upscope $end
$scope task stimuli $end
$var reg 3 & a [2:0] $end
$var reg 1 ' enable $end
$upscope $end
$upscope $end
$enddefinitions $end
#0
$dumpvars
x'
bx &
bz %
b0 $
0#
b0 "
bz !
$end
#5
0'
b0 &
#15
b1 "
b1 $
b1 &
#25
b111 "
b111 $
b111 &
#40
b0 !
b0 %
1#
b0 "
b0 $
1'
b0 &
#50
b1 !
b1 %
b1 "
b1 $
b1 &
#60
b10 !
b10 %
b10 "
b10 $
b10 &
#70
b11 !
b11 %
b11 "
b11 $
b11 &
#80
b100 !
b100 %
b100 "
b100 $
b100 &
#90
b101 !
b101 %
b101 "
b101 $
b101 &
#100
b110 !
b110 %
b110 "
b110 $
b110 &
#110
b111 !
b111 %
b111 "
b111 $
b111 &
