4 Bit Ripple Carry Adder using 1 bit RCA/rca_1bit.v
// Write a RTL code for 4 bit ripple carry adder using 1 bit 1 ripple carry
// adder





module rca_1(sum, carry, a, b, cin);
       output sum, carry;
       input a, b, cin;

       assign sum = a ^ b ^ cin;
       assign carry = (a & b) | cin & (a ^ b);

endmodule

4 Bit Ripple Carry Adder using 1 bit RCA/rca_4bit.v
// Write RTL code for 4 bit RCA using1 bit RCA



module rca_4(sum,carry,a,b,cin);
        
       output [3:0] sum;
       output carry;
       input [3:0] a;
       input [3:0] b;
       input cin;

       wire c1,c2,c3;

      rca_1 u1 (.sum(sum[0]), .carry(c1) , .a(a[0]), .b(b[0]) , .cin(cin));
      rca_1 u2 (.sum(sum[1]), .carry(c2) , .a(a[1]), .b(b[1]) , .cin(c1));
      rca_1 u3 (.sum(sum[2]), .carry(c3) , .a(a[2]), .b(b[2]) , .cin(c2));
      rca_1 u4 (.sum(sum[3]), .carry(carry) , .a(a[3]), .b(b[3]) , .cin(c3));

endmodule

4 Bit Ripple Carry Adder using 1 bit RCA/rca_4bit_tb.v
// Write a testbench code for 4bit RCA using 1bit RCA



module rca_4_tb();

   reg [3:0] a,b;
   reg cin;
   wire [3:0] sum;
   wire carry;


       rca_4 dut(
              .a(a),
	      .b(b),
	      .cin(cin),
              .sum(sum),
	      .carry(carry));

	     initial
	     begin
		     $dumpfile("dump.vcd");
		     $dumpvars;
		     $monitor( $time, "inputs: a=%b , b=%b , cin=%b , outputs:-- sum=%b , carry=%b", a,b,cin,sum,carry);

		     a = 4'b0000;; b = 4'b0000 ; cin = 0;
		     #10  a = 4'b1111 ; b = 4'b1111 ; cin = 1;
		     #10  a = 4'b0001 ; b = 4'b0001 ; cin = 0;
		     #10  a = 4'b0110 ; b = 4'b0110 ; cin = 1;
		     #10  a = 4'b0010 ; b = 4'b0010 ; cin = 0;
		     #10  a = 4'b0101 ; b = 4'b0101 ; cin = 1;
		     #10  a = 4'b0011 ; b = 4'b0011 ; cin = 0;
		     #10  a = 4'b0100 ; b = 4'b0100 ; cin = 1;
		     #10  a = 4'b0000 ; b = 4'b0000 ; cin = 0;
			  #10  a = 4'b1111 ; b = 4'b0001 ; cin = 1;
$finish;
		     #10;
		     
		    
	     end

endmodule

4 Bit Ripple Carry Adder using 1 bit RCA/dump.vcd
$date
	Wed Sep 17 22:30:37 2025
$end
$version
	Icarus Verilog
$end
$timescale
	1s
$end
$scope module rca_4_tb $end
$var wire 4 ! sum [3:0] $end
$var wire 1 " carry $end
$var reg 4 # a [3:0] $end
$var reg 4 $ b [3:0] $end
$var reg 1 % cin $end
$scope module dut $end
$var wire 4 & a [3:0] $end
$var wire 4 ' b [3:0] $end
$var wire 1 % cin $end
$var wire 4 ( sum [3:0] $end
$var wire 1 " carry $end
$var wire 1 ) c3 $end
$var wire 1 * c2 $end
$var wire 1 + c1 $end
$scope module u1 $end
$var wire 1 , a $end
$var wire 1 - b $end
$var wire 1 + carry $end
$var wire 1 % cin $end
$var wire 1 . sum $end
$upscope $end
$scope module u2 $end
$var wire 1 / a $end
$var wire 1 0 b $end
$var wire 1 * carry $end
$var wire 1 + cin $end
$var wire 1 1 sum $end
$upscope $end
$scope module u3 $end
$var wire 1 2 a $end
$var wire 1 3 b $end
$var wire 1 ) carry $end
$var wire 1 * cin $end
$var wire 1 4 sum $end
$upscope $end
$scope module u4 $end
$var wire 1 5 a $end
$var wire 1 6 b $end
$var wire 1 " carry $end
$var wire 1 ) cin $end
$var wire 1 7 sum $end
$upscope $end
$upscope $end
$upscope $end
$enddefinitions $end
#0
$dumpvars
07
06
05
04
03
02
01
00
0/
0.
0-
0,
0+
0*
0)
b0 (
b0 '
b0 &
0%
b0 $
b0 #
0"
b0 !
$end
#10
11
14
17
1+
1*
1)
1"
b1111 !
b1111 (
1.
1-
10
13
16
1,
1/
12
15
1%
b1111 $
b1111 '
b1111 #
b1111 &
#20
04
07
0*
0)
0"
b10 !
b10 (
0.
00
03
06
0/
02
05
0%
b1 $
b1 '
b1 #
b1 &
#30
01
14
17
0+
1*
1)
b1101 !
b1101 (
1.
0-
10
13
0,
1/
12
1%
b110 $
b110 '
b110 #
b110 &
#40
07
0)
b100 !
b100 (
0.
03
02
0%
b10 $
b10 '
b10 #
b10 &
#50
11
04
17
1+
0*
1)
b1011 !
b1011 (
1.
1-
00
13
1,
0/
12
1%
b101 $
b101 '
b101 #
b101 &
#60
14
07
1*
0)
b110 !
b110 (
0.
10
03
1/
02
0%
b11 $
b11 '
b11 #
b11 &
#70
01
04
17
0+
0*
1)
b1001 !
b1001 (
1.
0-
00
13
0,
0/
12
1%
b100 $
b100 '
b100 #
b100 &
#80
07
0)
b0 !
b0 (
0.
03
02
0%
b0 $
b0 '
b0 #
b0 &
#90
1"
1)
1*
1+
01
04
07
b1 !
b1 (
1.
1-
1,
1/
12
15
1%
b1 $
b1 '
b1111 #
b1111 &
