8x3PriorityEncoder/priority83.v
// Q2. Write a rtl code for 8:3 Priority Encoder and verify the same


module pe_83(Y,valid,D);
        output reg [2:0] Y;
	output reg valid;
	input [7:0]  D;

	always @(*) begin
		valid = 1'b1;
		casex (D)
			8'b00000000 : Y = 3'bxxx;
			8'b00000001 : Y = 3'b000;
			8'b0000001x : Y = 3'b001;
			8'b000001xx : Y = 3'b010;
			8'b00001xxx : Y = 3'b011;
			8'b0001xxxx : Y = 3'b100;
			8'b001xxxxx : Y = 3'b101;
			8'b01xxxxxx : Y = 3'b110;
			8'b1xxxxxxx : Y = 3'b111;
			default : Y = 3'dz; 
			
		endcase
	end

endmodule

8x3PriorityEncoder/priority83_tb.v
// Q2. Write a TB to verify 8:3 priority encoder

module pe_83_tb();
       wire [2:0] Y;
       wire valid;
       reg [7:0] D;

       pe_83 dut (
	       .Y(Y),
	       .valid(valid),
	       .D(D)
       );

       task initial_c;
	       begin
		       D = 8'd0;
		       #5;
		       $display($time,"input:--- D=%b, outputs:--- valid=%b , Y=%b", D, valid, Y);
	       end
       endtask

       task stimuli (input [7:0] d);
	       begin
		       D = d;
		       #5;
	       end
       endtask

       initial 
       begin
	       $display("----- 8:3 Priority Encoder-----");
			 $monitor($time, "inputs:--- D=%b , outputs:--- valid=%b , Y=%b ", D,valid,Y);
	       $dumpfile("dump.vcd");
	       $dumpvars(0, pe_83_tb);

	       initial_c;

	       // No active input
	       stimuli(8'd0);
			 #5;

	       // Sungle active input
	       stimuli(8'b00000001); #5;
			 stimuli(8'b00000010); #5;
	       stimuli(8'b00000100); #5;
	       stimuli(8'b00001000); #5;
	       stimuli(8'b00010000); #5;
	       stimuli(8'b00100000); #5;
	       stimuli(8'b01000000); #5;
	       stimuli(8'b10000000); #5;

	       // Multiple active inputs
	       stimuli(8'b10101010); #5;
	       stimuli(8'b01010101); #5;
	       stimuli(8'b00110011); #5;
	       stimuli(8'b11001100); #5;
	       stimuli(8'b00010001); #5;


	       
	       $finish;
       end


endmodule

8x3PriorityEncoder/dump.vcd
$date
	Wed Sep 24 22:36:10 2025
$end
$version
	Icarus Verilog
$end
$timescale
	1s
$end
$scope module pe_83_tb $end
$var wire 1 ! valid $end
$var wire 3 " Y [2:0] $end
$var reg 8 # D [7:0] $end
$scope module dut $end
$var wire 8 $ D [7:0] $end
$var reg 3 % Y [2:0] $end
$var reg 1 ! valid $end
$upscope $end
$scope task initial_c $end
$upscope $end
$scope task stimuli $end
$var reg 8 & d [7:0] $end
$upscope $end
$upscope $end
$enddefinitions $end
#0
$dumpvars
bx &
bx %
b0 $
b0 #
bx "
1!
$end
#5
b0 &
#15
b0 "
b0 %
b1 #
b1 $
b1 &
#25
b1 "
b1 %
b10 #
b10 $
b10 &
#35
b10 "
b10 %
b100 #
b100 $
b100 &
#45
b11 "
b11 %
b1000 #
b1000 $
b1000 &
#55
b100 "
b100 %
b10000 #
b10000 $
b10000 &
#65
b101 "
b101 %
b100000 #
b100000 $
b100000 &
#75
b110 "
b110 %
b1000000 #
b1000000 $
b1000000 &
#85
b111 "
b111 %
b10000000 #
b10000000 $
b10000000 &
#95
b10101010 #
b10101010 $
b10101010 &
#105
b110 "
b110 %
b1010101 #
b1010101 $
b1010101 &
#115
b101 "
b101 %
b110011 #
b110011 $
b110011 &
#125
b111 "
b111 %
b11001100 #
b11001100 $
b11001100 &
#135
b100 "
b100 %
b10001 #
b10001 $
b10001 &
