Bidirectional buffer/bidirectional_buffer.v
// Q6. Write a RTL code for bidirectional buffer and verify the same
//
//
module bidir_buff( control, a,b);

        input control;
	inout a,b;

	bufif1 b1(b, a, control);
	bufif0 b2(a, b, control);

endmodule

Bidirectional buffer/bidirectional_buffer_tb.v
// Q6. Write testbench to verify the bidirectional buffer 


module bidir_buff_tb();

      wire a,b;
      reg control;
      reg tempa, tempb;

      bidir_buff dut(
	      .control(control),
	      .a(a),
	      .b(b)
      );

      assign b = (control == 0) ? tempb : 1'bz;
      assign a = (control == 1) ? tempa : 1'bz;

      initial 
      begin
	      {tempa,tempb,control} = 0;
	      $monitor($time, "input control=%b , inout: a=%b , b=%b " , control,a,b);
	      $dumpfile("dump.vcd");
	      $dumpvars;
	      #300;
	      $finish;
      end

      always #10 tempa = ~tempa;
      always #10 tempb = ~tempb;
      always #50 control = ~control;

      
endmodule

Bidirectional buffer/dump.vcd
$date
	Sun Sep 21 21:50:11 2025
$end
$version
	Icarus Verilog
$end
$timescale
	1s
$end
$scope module bidir_buff_tb $end
$var wire 1 ! a $end
$var wire 1 " b $end
$var reg 1 # control $end
$var reg 1 $ tempa $end
$var reg 1 % tempb $end
$scope module dut $end
$var wire 1 ! a $end
$var wire 1 " b $end
$var wire 1 # control $end
$upscope $end
$upscope $end
$enddefinitions $end
#0
$dumpvars
0%
0$
0#
0"
0!
$end
#10
1!
1"
1%
1$
#20
0!
0"
0%
0$
#30
1!
1"
1%
1$
#40
0!
0"
0%
0$
#50
1%
1$
1"
1!
1#
#60
0"
0!
0%
0$
#70
1"
1!
1%
1$
#80
0"
0!
0%
0$
#90
1"
1!
1%
1$
#100
0%
0$
0!
0"
0#
#110
1!
1"
1%
1$
#120
0!
0"
0%
0$
#130
1!
1"
1%
1$
#140
0!
0"
0%
0$
#150
1%
1$
1"
1!
1#
#160
0"
0!
0%
0$
#170
1"
1!
1%
1$
#180
0"
0!
0%
0$
#190
1"
1!
1%
1$
#200
0%
0$
0!
0"
0#
#210
1!
1"
1%
1$
#220
0!
0"
0%
0$
#230
1!
1"
1%
1$
#240
0!
0"
0%
0$
#250
1%
1$
1"
1!
1#
#260
0"
0!
0%
0$
#270
1"
1!
1%
1$
#280
0"
0!
0%
0$
#290
1"
1!
1%
1$
#300
0%
0$
0!
0"
0#
