Full Adder/fa.v
// Write a RTL Code for 1 bit Full Adder using Dataflow abstraction



module q1(
                output sum,
	        output cout,
	        input a,
	        input b, 
	        input cin);

  assign sum = a ^ b ^ cin;
  assign cout = (a & b) | (b & cin) | (a & cin);


endmodule

Full Adder/fa_tb.v
// Write testbench for 1 bit full adder to verufy





module q1_tb();
  
   wire sum , cout;
   reg a, b, cin;
  
   q1 dut (
	   .a(a),
	   .b(b),
	   .cin(cin),
	   .sum(sum),
	   .cout(cout)
           );

	   initial
	   begin
		   a = 0 ; b = 0 ; cin = 0;
		   #5 a = 1 ; b = 1 ; cin = 1;
		   #5 a = 0 ; b = 0 ; cin = 1;
		   #5 a = 1 ; b = 1 ; cin = 0;
		   #5 a = 0 ; b = 1 ; cin = 0;
		   #5 a = 1 ; b = 0 ; cin = 1;
		   #5 a = 0 ; b = 1 ; cin = 1;
		   #5 a = 1 ; b = 0 ; cin = 0;
		   $finish;
	   end

	   initial 
	   begin
		   $monitor ( $time, " inputs:--- a=%d , b=%d , cin=%d outputs:--- sum=%d , cout=%d", a,b,cin,sum,cout);
		   
	   end

	   initial 
	   begin
		   $dumpfile("dump.vcd");
		   $dumpvars;
	   end


                



endmodule

Full Adder/dump.vcd
$date
	Wed Sep 17 17:15:35 2025
$end
$version
	Icarus Verilog
$end
$timescale
	1s
$end
$scope module q1_tb $end
$var wire 1 ! sum $end
$var wire 1 " cout $end
$var reg 1 # a $end
$var reg 1 $ b $end
$var reg 1 % cin $end
$scope module dut $end
$var wire 1 # a $end
$var wire 1 $ b $end
$var wire 1 % cin $end
$var wire 1 " cout $end
$var wire 1 ! sum $end
$upscope $end
$upscope $end
$enddefinitions $end
#0
$dumpvars
0%
0$
0#
0"
0!
$end
#5
1"
1!
1%
1$
1#
#10
0"
0$
0#
#15
1"
0!
0%
1$
1#
#20
0"
1!
0#
#25
1"
0!
1%
0$
1#
#30
1"
1$
0#
#35
0"
1!
0%
0$
1#
