4x1 Mux using Decoder and Tri-state Buffers/trisatebuffer.v
// Q5. Write RTL code for 4:1 mux using decoder and tri-state buffers



module buffers_tristate( Y,A,en);

       output Y;
       input A;
       input en;

       assign Y = en ? A : 1'bz;

endmodule

4x1 Mux using Decoder and Tri-state Buffers/decoder2x4.v
// Q5. Write code rtl code for 4x1 Mux using decoder and tristate buffers


module decoder2to4(
                   input [1:0] A,
		   input en,
	           output [3:0] Y);


		   assign Y[0] = en & (~A[1]) & (~A[0]);
		   assign Y[1] = en & (~A[1]) & A[0];
		   assign Y[2] = en & A[1] & (~A[0]);
		   assign Y[3] = en & A[1] & A[0];

endmodule

4x1 Mux using Decoder and Tri-state Buffers/mux41.v


// Q5. Write RTL code for 4x1 Mux using Decoder and tristate buffers



module mux_41(Y,I,sel,en);

        output Y;
	input [3:0] I;
	input [1:0] sel;
	input en;

	wire [3:0] d;

	decoder2to4 u1 ( .A(sel) , .en(en) , .Y(d) );

	buffers_tristate t0 ( .Y(Y), .A(I[0]), .en(d[0]) );
	buffers_tristate t1 ( .Y(Y), .A(I[1]), .en(d[1]) );
   buffers_tristate t2 ( .Y(Y), .A(I[2]), .en(d[2]) );
	buffers_tristate t3 ( .Y(Y), .A(I[3]), .en(d[3]) );

	




endmodule

4x1 Mux using Decoder and Tri-state Buffers/mux41_tb.v
// Q5. Write testbench for 4x1 mux using decoder and tristate buffer



module mux_41_tb();

       wire Y;
       reg [3:0] I;
       reg [1:0] sel;
       reg en;

       mux_41 dut(
       .I(I),
       .sel(sel),
       .en(en),
       .Y(Y)
);
       initial
       begin
	       $dumpfile("dump.vcd");
	       $dumpvars;
	       $monitor( $time,"inputs:-- I=%b , sel=%b , en=%b , outputs:-- Y=%b", I,sel,en,Y);
	       //case 1: en=0, output must be Z
	       en = 0 ; I = 4'b1010 ; sel = 2'b00;
	       #10;
	       en = 1 ; I = 4'b1010 ; sel = 2'b00; //op = I0
	       #10;
	       sel = 2'b01; // op = I1. input remains same
	       #10;
	       sel = 2'b10;
	       #10;
	       sel = 2'b11;
	       #10;
	       I = 4'b0101 ; sel = 2'b10;
	       #10;
	       I = 4'b0110 ; sel = 2'b11;
	       #10
	       I = 4'b0000 ; sel = 2'b01;
	       #10;
	       $finish;
       end


endmodule

4x1 Mux using Decoder and Tri-state Buffers/dump.vcd
$date
	Wed Sep 17 22:43:19 2025
$end
$version
	Icarus Verilog
$end
$timescale
	1s
$end
$scope module mux_41_tb $end
$var wire 1 ! Y $end
$var reg 4 " I [3:0] $end
$var reg 1 # en $end
$var reg 2 $ sel [1:0] $end
$scope module dut $end
$var wire 4 % I [3:0] $end
$var wire 1 ! Y $end
$var wire 1 # en $end
$var wire 2 & sel [1:0] $end
$var wire 4 ' d [3:0] $end
$scope module t0 $end
$var wire 1 ( A $end
$var wire 1 ! Y $end
$var wire 1 ) en $end
$upscope $end
$scope module t1 $end
$var wire 1 * A $end
$var wire 1 ! Y $end
$var wire 1 + en $end
$upscope $end
$scope module t2 $end
$var wire 1 , A $end
$var wire 1 ! Y $end
$var wire 1 - en $end
$upscope $end
$scope module t3 $end
$var wire 1 . A $end
$var wire 1 ! Y $end
$var wire 1 / en $end
$upscope $end
$scope module u1 $end
$var wire 2 0 A [1:0] $end
$var wire 1 # en $end
$var wire 4 1 Y [3:0] $end
$upscope $end
$upscope $end
$upscope $end
$enddefinitions $end
#0
$dumpvars
b0 1
b0 0
0/
1.
0-
0,
0+
1*
0)
0(
b0 '
b0 &
b1010 %
b0 $
0#
b1010 "
z!
$end
#10
0!
1)
b1 '
b1 1
1#
#20
0)
1!
1+
b10 '
b10 1
b1 $
b1 &
b1 0
#30
0)
0!
1-
0+
b100 '
b100 1
b10 $
b10 &
b10 0
#40
0-
1!
1/
b1000 '
b1000 1
b11 $
b11 &
b11 0
#50
1-
0/
b100 '
b100 1
1!
1(
0*
1,
0.
b10 $
b10 &
b10 0
b101 "
b101 %
#60
0-
0!
1/
b1000 '
b1000 1
0(
1*
b11 $
b11 &
b11 0
b110 "
b110 %
#70
1+
0!
0/
b10 '
b10 1
0*
0,
b1 $
b1 &
b1 0
b0 "
b0 %
