Full Adder Using Half Adder/half_adder.v

  
module half_adder(input a,b,
	          output sum,carry);
				 
   // Data-flow abstraction
   assign sum   = a ^ b;
   assign carry = a & b;

endmodule

Full Adder Using Half Adder/full_adder.v
/********************************************************************************************
Copyright 2019 - Maven Silicon Softech Pvt Ltd. 
 
All Rights Reserved.

This source code is an unpublished work belongs to Maven Silicon Softech Pvt Ltd.

It is not to be shared with or used by any third parties who have not enrolled for our paid training 

courses or received any written authorization from Maven Silicon.


Webpage     :      www.maven-silicon.com

Filename    :	   full_adder.v   

Description :      One bit Full adder Design

Author Name :      Susmita

Version     : 	   1.0
*********************************************************************************************/

module full_adder( a, b, cin,sum, carry);


   //Step1 : Write down the directions for the ports

   
   input a, b, cin ;  
   output sum, carry;	

   //Step2 : Declare the internal wires    
   // Since this full adder is implemented using half adders which would
   // require us to use internal wires
   wire s1, c1,c2;
   //Step3 : Instantiate the Half-Adders using name-based port mapping	
   half_adder u1( a, b,s1, c1);
   half_adder u2( s1, cin,sum, c2);   
 
   //Step4 : Instantiate the OR gate
   or u3(carry, c1, c2);

endmodule

Full Adder Using Half Adder/fa_tb.v
module fa_tb();
// Step1: for outputs : reg ; for inputs: wire
   wire sum , carry ;
   reg a,b,cin;

// Step2: DUT instantiation by name ( not to practice by position postion)
    
   full_adder dut(
       .a(a),
       .b(b),
       .cin(cin),
       .sum(sum),
       .carry(carry)
   );

// Step3: Generate stimulus for inputs

    initial
    begin
	     a = 0 ; b = 0 ; cin = 0;
	  #5 a = 1 ; b = 0 ; cin = 1;
	  #5 a = 0 ; b = 1 ; cin = 0;
	  #5 a = 1 ; b = 1 ; cin = 1;
	  #5 a = 0 ; b = 0 ; cin = 1;
	  #5 a = 1 ; b = 0 ; cin = 0;
	  #5 a = 1 ; b = 1 ; cin = 0;
	  #5 a = 0 ; b = 1 ; cin = 1;
	  #5 a = 0 ; b = 0 ; cin = 0;
	  #5 a = 1 ; b = 1 ; cin = 1;
	   $finish;
   end

//Step4: Monitoring  / Displaying inputs and outputs response
 
  initial
  begin
	  $monitor ( $time , " inputs:--- a=%d , b=%d , cin=%d outputs:--- sum=%d , carry=%d", a,b,cin,sum,carry);
	 
  end
//Step5: To view the waveform for analysis

  initial
  begin
	  $dumpfile("dump.vcd");
	  $dumpvars;
  end




endmodule

Full Adder Using Half Adder/dump.vcd
$date
	Wed Sep 17 22:45:41 2025
$end
$version
	Icarus Verilog
$end
$timescale
	1s
$end
$scope module fa_tb $end
$var wire 1 ! sum $end
$var wire 1 " carry $end
$var reg 1 # a $end
$var reg 1 $ b $end
$var reg 1 % cin $end
$scope module dut $end
$var wire 1 # a $end
$var wire 1 $ b $end
$var wire 1 " carry $end
$var wire 1 % cin $end
$var wire 1 ! sum $end
$var wire 1 & s1 $end
$var wire 1 ' c2 $end
$var wire 1 ( c1 $end
$scope module u1 $end
$var wire 1 # a $end
$var wire 1 $ b $end
$var wire 1 ( carry $end
$var wire 1 & sum $end
$upscope $end
$scope module u2 $end
$var wire 1 & a $end
$var wire 1 % b $end
$var wire 1 ' carry $end
$var wire 1 ! sum $end
$upscope $end
$upscope $end
$upscope $end
$enddefinitions $end
#0
$dumpvars
0(
0'
0&
0%
0$
0#
0"
0!
$end
#5
1"
1'
1&
1%
1#
#10
0"
1!
0'
0%
1$
0#
#15
1"
0&
1(
1%
1#
#20
0"
0(
0$
0#
#25
1&
0%
1#
#30
0!
1"
0&
1(
1$
#35
1'
1&
0(
1%
0#
#40
0"
0'
0&
0%
0$
#45
1"
1!
1(
1%
1$
1#
