Configurable N-bit Counter/modecount.v
`timescale 1ns / 1ps
//////////////////////////////////////////////////////////////////////////////////
// Company: 
// Engineer: 
// 
// Create Date:    20:37:14 11/01/2025 
// Design Name: 
// Module Name:    modecount 
// Project Name: 
// Target Devices: 
// Tool versions: 
// Description: Mode counter is a configurable counter tha can be a Up counter, Down COunter, Johnson Counter and Ring counter.
//
// Dependencies: 
//
// Revision: 
// Revision 0.01 - File Created
// Additional Comments: 
//
//////////////////////////////////////////////////////////////////////////////////
module modecount #(parameter N = 4) (   // Parameterized version
    input clk,
    input rst,
    input en,
    input [1:0] mode,
    output reg [N-1:0] count
);

    always @(posedge clk) begin
        if (rst)
            count <= {N{1'b0}};   // Reset to all zeros
        else if (en) begin
            case (mode)
                2'b00: count <= count + 1'b1;                   // Up counter
                2'b01: count <= count - 1'b1;                   // Down counter
                2'b10: count <= {count[N-2:0], count[N-1]};     // Rotate left
                2'b11: count <= {count[0], count[N-1:1]};       // Rotate right
                default: count <= count;
            endcase
        end
    end
endmodule

Configurable N-bit Counter/modecount_tb.v
`timescale 1ns / 1ps

////////////////////////////////////////////////////////////////////////////////
// Company: 
// Engineer:
//
// Create Date:   21:55:15 11/01/2025
// Design Name:   modecount
// Module Name:   /home/tejasbaru/Verilog/Mode Counter/modecounter/modecount_tb.v
// Project Name:  modecounter
// Target Device:  
// Tool versions:  
// Description: 
//
// Verilog Test Fixture created by ISE for module: modecount
//
// Dependencies:
// 
// Revision:
// Revision 0.01 - File Created
// Additional Comments:
// 
////////////////////////////////////////////////////////////////////////////////

`timescale 1ns/1ps

module tb_modecount;
    parameter N = 4;

    reg clk, rst, en;
    reg [1:0] mode;
    wire [N-1:0] count;

    // Instantiate DUT
    modecount #(N) dut (
        .clk(clk),
        .rst(rst),
        .en(en),
        .mode(mode),
        .count(count)
    );

    // Localparams for readability
    localparam [1:0]
        UP   = 2'b00,
        DOWN = 2'b01,
        ROTL = 2'b10,
        ROTR = 2'b11;

    // Clock generation
    always #5 clk = ~clk;  // 10 ns period

    // Task for reset
    task reset_dut;
        begin
            $display("\n[Resetting DUT]");
            rst = 1; en = 0;
            @(posedge clk);
            rst = 0;
        end
    endtask

    // Task for stimulus
    task stimulus(input [1:0] mode_sel, input integer cycles);
        begin
            mode = mode_sel;
            en = 1;
            case (mode_sel)
                UP:   $display("\nMode = UP (%0d cycles)", cycles);
                DOWN: $display("\nMode = DOWN (%0d cycles)", cycles);
                ROTL: $display("\nMode = ROTATE LEFT (%0d cycles)", cycles);
                ROTR: $display("\nMode = ROTATE RIGHT (%0d cycles)", cycles);
            endcase
            repeat(cycles) @(posedge clk);
            en = 0;
        end
    endtask

    // Main sequence
    initial begin
        // Dump for GTKWave or ModelSim
        $dumpfile("modecount_tb.vcd");
        $dumpvars(0, tb_modecount);

        // Initialize
        clk = 0; rst = 0; en = 0; mode = UP;

        // Apply reset
        reset_dut();

        // Start monitoring
        $monitor("Time=%0t | clk=%b rst=%b en=%b mode=%b | count=%b",
                 $time, clk, rst, en, mode, count);

        // Run for each mode
        stimulus(UP,   5);
        stimulus(DOWN, 4);
        stimulus(ROTL, 3);
        stimulus(ROTR, 6);

        $display("\nSimulation Complete.");
        $finish;
    end
endmodule

Configurable N-bit Counter/modecount_tb.vcd
$date
   Sat Nov  1 23:36:56 2025
$end
$version
  P.20131013
$end
$timescale
  1ps
$end
$scope module tb_modecount $end
$var wire 1 ! count [3] $end
$var wire 1 " count [2] $end
$var wire 1 # count [1] $end
$var wire 1 $ count [0] $end
$var reg 1 % clk $end
$var reg 1 & rst $end
$var reg 1 ' en $end
$var reg 2 ( mode [1:0] $end
$scope task reset_dut $end
$upscope $end
$scope task stimulus $end
$var reg 2 ) mode_sel [1:0] $end
$var integer 32 * cycles $end
$upscope $end
$scope module dut $end
$var wire 1 + clk $end
$var wire 1 , rst $end
$var wire 1 - en $end
$var wire 1 . mode [1] $end
$var wire 1 / mode [0] $end
$var reg 4 0 count [3:0] $end
$upscope $end
$upscope $end
$enddefinitions $end
#0
$dumpvars
0.
0%
1&
0'
b0 (
bx )
bx *
bx 0
0+
1,
0-
0/
x$
x#
x"
x!
$end
#5000
1%
0&
1'
b0 )
b101 *
b0 0
1+
0,
1-
0$
0#
0"
0!
#10000
0%
0+
#15000
1%
b1 0
1+
1$
#20000
0%
0+
#25000
1%
b10 0
1+
0$
1#
#30000
0%
0+
#35000
1%
b11 0
1+
1$
#40000
0%
0+
#45000
1%
b100 0
1+
0$
0#
1"
#50000
0%
0+
#55000
1%
1'
b1 (
b1 )
b100 *
b101 0
1+
1/
1$
#60000
0%
0+
#65000
1%
b100 0
1+
0$
#70000
0%
0+
#75000
1%
b11 0
1+
1$
1#
0"
#80000
0%
0+
#85000
1%
b10 0
1+
0$
#90000
0%
0+
#95000
1.
1%
1'
b10 (
b10 )
b11 *
b1 0
1+
0/
1$
0#
#100000
0%
0+
#105000
1%
b10 0
1+
0$
1#
#110000
0%
0+
#115000
1%
b100 0
1+
0#
1"
#120000
0%
0+
#125000
1%
1'
b11 (
b11 )
b110 *
b1000 0
1+
1/
0"
1!
#130000
0%
0+
#135000
1%
b100 0
1+
1"
0!
#140000
0%
0+
#145000
1%
b10 0
1+
1#
0"
#150000
0%
0+
#155000
1%
b1 0
1+
1$
0#
#160000
0%
0+
#165000
1%
b1000 0
1+
0$
1!
#170000
0%
0+
#175000
1%
b100 0
1+
1"
0!
#180000
0%
0+
#185000
1%
0'
1+
