4x1Mux_Behav/mux4_1.v

module mux4_1(data_in,
	      sel_in,
	      y);

   //Step1 : Define the port directions with proper size & datatypes 
   input [3:0] data_in;
   input [1:0] sel_in;
   output reg y;

   //Step2 : Write the MUX behaviour as a parallel logic using "case" 
   always@ (*) begin
	   case (sel_in)
		   2'b00 : y = data_in[0];
		   2'b01 : y = data_in[1];
		   2'b10 : y = data_in[2];
		   2'b11 : y = data_in[3];
		   default: y = 1'bz;
	   endcase
   end


endmodule

4x1Mux_Behav/mux4_1_tb.v


module mux4_1_tb();

   //Step1 : Write down the variables required for testbench
   reg [3:0] data_in;
   reg [1:0] sel_in;
   wire y;
   
								
   //Step2 : Instantiate the Design 
    mux4_1 dut(
       .data_in(data_in),
       .sel_in(sel_in),
       .y(y)
 );   

   //Step3 : Declare a task to initialize inputs of DUT to 0 

   task initial_c;
	   begin 
	   data_in = 4'b0000;
	   sel_in = 2'b00;
	   #10;
	   $display($time, "inputs:--- data_in=%b , sel_in=%b , output:--- y=%b ", data_in,sel_in,y);
   end
   endtask

     //Step4 : Declare  tasks with arguments for driving stimulus to DUT 
      task stimuli(input [3:0] d, input [1:0] sel);
	   begin
		   data_in = d;
		   sel_in = sel;
		   #10;
		   $display($time, "inputs:-- data_in=%b , sel_in=%b , outputs:--- y=%b", data_in,sel_in,y);

	   end
   endtask

   //Step5 : Call the tasks from procedural process 

   initial
   begin
	   $display("-----4:1 MUX using Behavioral abstraction-----");
	   $dumpfile("dump.vcd");
	   $dumpvars(0,mux4_1_tb);

	   initial_c;

	   stimuli(4'b0101 , 2'b00); #5;
	   stimuli(4'b0101 , 2'b01); #5;
	   stimuli(4'b0101 , 2'b10); #5;
	   stimuli(4'b0101 , 2'b11); #5;
	   
	   #5;
	   stimuli(4'b1010 , 2'b00); #5;
	   stimuli(4'b1010 , 2'b01); #5;
	   stimuli(4'b1010 , 2'b10); #5;
	   stimuli(4'b1010 , 2'b11); #5;
	   #5;
	      
   

   //Step6 : Use $monitor task to display inputs and outputs
   $monitor($time,"inputs:--- data_in=%b , sel_in=%b , output:--- y=%b", data_in,sel_in,y);

   //Step7 : Use $finish task to terminate the simulation at 100ns
    $finish;

   end

   
endmodule

4x1Mux_Behav/dump.vcd
$date
	Wed Sep 24 22:15:58 2025
$end
$version
	Icarus Verilog
$end
$timescale
	1s
$end
$scope module mux4_1_tb $end
$var wire 1 ! y $end
$var reg 4 " data_in [3:0] $end
$var reg 2 # sel_in [1:0] $end
$scope module dut $end
$var wire 4 $ data_in [3:0] $end
$var wire 2 % sel_in [1:0] $end
$var reg 1 ! y $end
$upscope $end
$scope task initial_c $end
$upscope $end
$scope task stimuli $end
$var reg 4 & d [3:0] $end
$var reg 2 ' sel [1:0] $end
$upscope $end
$upscope $end
$enddefinitions $end
#0
$dumpvars
bx '
bx &
b0 %
b0 $
b0 #
b0 "
0!
$end
#10
1!
b101 "
b101 $
b0 '
b101 &
#25
0!
b1 #
b1 %
b1 '
#40
1!
b10 #
b10 %
b10 '
#55
0!
b11 #
b11 %
b11 '
#75
b0 #
b0 %
b1010 "
b1010 $
b0 '
b1010 &
#90
1!
b1 #
b1 %
b1 '
#105
0!
b10 #
b10 %
b10 '
#120
1!
b11 #
b11 %
b11 '
