4x1 Mux Using 2x1 Mux/mux_21.v
// Q4 Write a RTL code for 4:1 mux using 2:1 mux and verify the same
//



module mux_21( Y, I , sel);

       output Y;
       input [1:0] I;
       input sel;

       // using continuous assignment

       assign Y = ( sel == 1'b0 )? I[0] :
	       I[1] ;

endmodule

4x1 Mux Using 2x1 Mux/mux_41.v
// Q4 Write a RTL code for 4:1 mux using 2:1 mux



module mux_41(Y,I,sel);

       output Y;
       input [1:0] sel;
       input [3:0] I;

       wire M0, M1;

       mux_21 u1(.Y(M0), .I(I[1:0]), .sel(sel[0]));
       mux_21 u2(.Y(M1), .I(I[3:2]), .sel(sel[0]));
       mux_21 u3(.Y(Y), .I({M1,M0}), .sel(sel[1]));

endmodule

4x1 Mux Using 2x1 Mux/mux_41_tb.v
// Q4 Write a testbench for 4:1 mux using 2:1 mux



module mux_41_tb();

          reg[3:0] I;
	  reg[1:0] sel;
	  wire Y;

	   mux_41 dut (
	         .Y(Y),
	         .I(I),
	         .sel(sel)
	 );
         initial
	     begin
		
		$dumpfile("dump.vcd");
		$dumpvars;	
		
		$monitor ($time, " inputs:-- I=%b , sel=%b , outputs:--Y=%b ", I,sel,Y);
 // Test I0
    I = 4'b0001;
    sel = 2'b00; #10;
    sel = 2'b01; #10;
    sel = 2'b10; #10;
    sel = 2'b11; #10;

    // Test I1
    I = 4'b0010;
    sel = 2'b00; #10;
    sel = 2'b01; #10;
    sel = 2'b10; #10;
    sel = 2'b11; #10;

    // Test I2
    I = 4'b0100;
    sel = 2'b00; #10;
    sel = 2'b01; #10;
    sel = 2'b10; #10;
    sel = 2'b11; #10;

    // Test I3
    I = 4'b1000;
    sel = 2'b00; #10;
    sel = 2'b01; #10;
    sel = 2'b10; #10;
    sel = 2'b11; #10;
   
     $finish;
	  
	  end

endmodule

4x1 Mux Using 2x1 Mux/dump.vcd
$date
	Wed Sep 17 22:34:39 2025
$end
$version
	Icarus Verilog
$end
$timescale
	1s
$end
$scope module mux_41_tb $end
$var wire 1 ! Y $end
$var reg 4 " I [3:0] $end
$var reg 2 # sel [1:0] $end
$scope module dut $end
$var wire 4 $ I [3:0] $end
$var wire 2 % sel [1:0] $end
$var wire 1 ! Y $end
$var wire 1 & M1 $end
$var wire 1 ' M0 $end
$scope module u1 $end
$var wire 2 ( I [1:0] $end
$var wire 1 ) sel $end
$var wire 1 ' Y $end
$upscope $end
$scope module u2 $end
$var wire 2 * I [1:0] $end
$var wire 1 + sel $end
$var wire 1 & Y $end
$upscope $end
$scope module u3 $end
$var wire 2 , I [1:0] $end
$var wire 1 - sel $end
$var wire 1 ! Y $end
$upscope $end
$upscope $end
$upscope $end
$enddefinitions $end
#0
$dumpvars
0-
b1 ,
0+
b0 *
0)
b1 (
1'
0&
b0 %
b1 $
b0 #
b1 "
1!
$end
#10
0!
b0 ,
0'
1)
1+
b1 #
b1 %
#20
b1 ,
1'
0)
0+
1-
b10 #
b10 %
#30
b0 ,
0'
1)
1+
b11 #
b11 %
#40
0)
0+
0-
b10 (
b0 #
b0 %
b10 "
b10 $
#50
1!
b1 ,
1'
1)
1+
b1 #
b1 %
#60
b0 ,
0'
0!
0)
0+
1-
b10 #
b10 %
#70
b1 ,
1'
1)
1+
b11 #
b11 %
#80
1&
0!
b10 ,
0'
0)
0+
0-
b0 (
b1 *
b0 #
b0 %
b100 "
b100 $
#90
b0 ,
0&
1)
1+
b1 #
b1 %
#100
1!
b10 ,
1&
0)
0+
1-
b10 #
b10 %
#110
0!
b0 ,
0&
1)
1+
b11 #
b11 %
#120
0)
0+
0-
b10 *
b0 #
b0 %
b1000 "
b1000 $
#130
b10 ,
1&
1)
1+
b1 #
b1 %
#140
b0 ,
0&
0!
0)
0+
1-
b10 #
b10 %
#150
1!
b10 ,
1&
1)
1+
b11 #
b11 %
