ALU/alu.v
/********************************************************************************************
Copyright 2019 - Maven Silicon Softech Pvt Ltd. 

All Rights Reserved.

This source code is an unpublished work belongs to Maven Silicon Softech Pvt Ltd.

It is not to be shared with or used by any third parties who have not enrolled for our paid training 

courses or received any written authorization from Maven Silicon.


Webpage     :      www.maven-silicon.com

Filename    :	   alu.v   

Description :      Arithmetic Logic Unit Design

Author Name :      Susmita

Version     :      1.0
*********************************************************************************************/

module alu(input signed [7:0]a_in,b_in,
           input [3:0]command_in,
	   input oe,
	   output signed [15:0]d_out);

   parameter ADD  = 4'b0000, // Add two 8 bit numbers a and b.
	     INC  = 4'b0001, // Increment a by 1. 
	     SUB  = 4'b0010, // Subtracts b from a.
	     DEC  = 4'b0011, // Decrement a by 1.
	     MUL  = 4'b0100, // Multiply 4 bit numbers a and b.
	     DIV  = 4'b0101, // Divide a by b.
	     SHL  = 4'b0110, // Shift a to left side by 1 bit.
	     SHR  = 4'b0111, // Shift a to right by 1 bit.
	     AND  = 4'b1000, // Logical AND operation
	     OR   = 4'b1001, // Logical OR operation
	     INV  = 4'b1010, // Logical Negation
	     NAND = 4'b1011, // Bitwise NAND
	     NOR  = 4'b1100, // Bitwise NOR
	     XOR  = 4'b1101, // Bitwise XOR
	     XNOR = 4'b1110, // Bitwise XNOR
	     BUF  = 4'b1111; // BUF

   //Internal variable used during ALU operation
   reg  [15:0]out;


   /*Step1 : Write down the functionality of ALU based on the commands given above.
	        *Use arithmetic and logical operators* */
   always@(*)
      begin
	 case(command_in)
            //--------- write the functionality here -------  
	   //Arithmetic
	   ADD: out = a_in + b_in;
	   INC: out = a_in + 1;
	   SUB: out = a_in - b_in;
	   DEC: out = a_in - 8'd1;
	   MUL: out = a_in * b_in ; //a_in[3:0] * b_in[3:0]
	   DIV: out = (b_in != 0) ? (a_in/b_in) : 16'hFFFF;
	   SHL: out = a_in << 1;
	   SHR: out = a_in >> 1;
	   //Logical
	   AND: out = {15'b0, (a_in && b_in)};
	   OR : out = {15'b0, (a_in || b_in)};
	   INV: out = {15'b0, (!a_in)};
	   //Bitwise
	   NAND:out = {8'b0, ~(a_in & b_in)};
	   NOR: out = {8'b0, ~(a_in | b_in)};
	   XOR: out = {8'b0, (a_in ^ b_in)};
	   XNOR:out = {8'b0, ~(a_in ^ b_in)};
	   BUF: out = {8'b0, a_in};
		default: out = 16'h0000;   // add default
		
	 endcase
      end

   //Understand the tri-state logic for actual output
   assign d_out = (oe) ? out : 16'hzzzz;
		
endmodule

ALU/alu_tb.v
/********************************************************************************************
Copyright 2019 - Maven Silicon Softech Pvt Ltd. 
 
All Rights Reserved.

This source code is an unpublished work belongs to Maven Silicon Softech Pvt Ltd.

It is not to be shared with or used by any third parties who have not enrolled for our paid training 

courses or received any written authorization from Maven Silicon.


Webpage     :      www.maven-silicon.com

Filename    :	   alu_tb.v   

Description :      Arithmetic Logic Unit Design Testbench

Author Name :      Susmita

Version     :      1.0
*********************************************************************************************/
module alu_tb();
    
   //Testbench global variables
   reg signed [7:0]a,b;
   reg [3:0]command;
   reg enable;
   wire signed [15:0]out;
	
   //Variables for iteration of the loops 
   integer m,n,o;

   //Parameter constants used for displaying the strings during operation
   parameter ADD  = 4'b0000, // Add two 8 bit numbers a and b.
  	     INC  = 4'b0001, // Increment a by 1. 
	     SUB  = 4'b0010, // Subtracts b from a.
	     DEC  = 4'b0011, // Decrement a by 1.
	     MUL  = 4'b0100, // Multiply 4 bit numbers a and b.
	     DIV  = 4'b0101, // Divide a by b.
	     SHL  = 4'b0110, // Shift a to left side by 1 bit.
	     SHR  = 4'b0111, // Shift a to right by 1 bit.
	     AND  = 4'b1000, // Logical AND operation
	     OR   = 4'b1001, // Logical OR operation
	     INV  = 4'b1010, // Logical Negation
	     NAND = 4'b1011, // Bitwise NAND
	     NOR  = 4'b1100, // Bitwise NOR
	     XOR  = 4'b1101, // Bitwise XOR
	     XNOR = 4'b1110, // Bitwise XNOR
	     BUF  = 4'b1111; // BUF
		  
					
   //Internal register for storing the string values
   reg [4*8:0]string_cmd;

   //Step1 : Instantiate the design ALU

   alu dut (
        .a_in(a),
        .b_in(b),
	.command_in(command),
	.oe(enable),
	.d_out(out)
	);

   //Step2 : Write a task named "initialize" to initialize the inputs of DUT
   //
   task initialize;
	   begin
		   a = 8'd0;
		   b = 8'd0;
		   command = 4'd0;
		   enable = 1'b0;
	   end
   endtask



   //Tasks used for generating stimulus
   task en_oe(input i);
      begin
         enable=i;
      end
   endtask

   task inputs(input [7:0]j,k);
      begin
	 a=j;
	 b=k;
      end
   endtask

   task cmd (input [3:0]l);
      begin
         command=l;
      end
   endtask

   task delay();
      begin
	 #10;
      end
   endtask
		
   //Process to hold the string values as per the commands.
   always@(command)
      begin
         case(command)
	    ADD    :  string_cmd = "ADD";
	    INC    :  string_cmd = "INC";
	    SUB    :  string_cmd = "SUB";
	    DEC    :  string_cmd = "DEC";
	    MUL    :  string_cmd = "MUL";
	    DIV    :  string_cmd = "DIV";
	    SHL    :  string_cmd = "SHL";
	    SHR    :  string_cmd = "SHR";
	    INV    :  string_cmd = "INV";
	    AND    :  string_cmd = "AND";
	    OR     :  string_cmd = "OR";
	    NAND   :  string_cmd = "NAND";
	    NOR    :  string_cmd = "NOR";
	    XOR    :  string_cmd = "XOR";
	    XNOR   :  string_cmd = "XNOR";
	    BUF    :  string_cmd = "BUF";
	    default : string_cmd = "UNKN";
	 endcase
      end
			
   //Process used for generating stimulus by calling tasks & passing values
   initial
      begin
	 initialize;
	 en_oe(1'b1);
	 for(m=0;m<16;m=m+1)
	    begin
	       for(n=0;n<16;n=n+1)
	          begin
	             inputs(m,n);
		     for(o=0;o<16;o=o+1)
			begin
			   command=o;
			   delay;
			end 
	          end
            end  
         en_oe(0);
         inputs(8'd20,8'd10);
         cmd(ADD);
         delay;
         en_oe(1);
         inputs(8'd25,8'd17);
         cmd(ADD);
         delay;  
         $finish;
      end
			
   //Process to monitor the changes in the variables	
   initial 
     // $monitor("Input oe=%b, a=%b, b=%b, command=%s, Output out=%b",enable,a,b,string_cmd,out);
	     $monitor("time=%0t | a=%d | b=%d | out=%d", $time, a, b, out);

  //Waveform dump
   initial
    begin
	    $dumpfile("dump.vcd");
	    $dumpvars(0, alu_tb.a, alu_tb.b, alu_tb.out);;
    end
								
   
endmodule

ALU/dump.vcd
$date
	Sun Sep 21 20:00:12 2025
$end
$version
	Icarus Verilog
$end
$timescale
	1s
$end
$scope module alu_tb $end
$var reg 8 ! a [7:0] $end
$upscope $end
$scope module alu_tb $end
$var reg 8 " b [7:0] $end
$upscope $end
$scope module alu_tb $end
$var wire 16 # out [15:0] $end
$upscope $end
$enddefinitions $end
#0
$dumpvars
b0 #
b0 "
b0 !
$end
#10
b1 #
#20
b0 #
#30
b1111111111111111 #
#40
b0 #
#50
b1111111111111111 #
#60
b0 #
#100
b1 #
#110
b11111111 #
#130
b0 #
#140
b11111111 #
#150
b0 #
#160
b1 #
b1 "
#180
b1111111111111111 #
#200
b0 #
#250
b1 #
#270
b11111111 #
#280
b11111110 #
#290
b1 #
#300
b11111110 #
#310
b0 #
#320
b10 #
b10 "
#330
b1 #
#340
b1111111111111110 #
#350
b1111111111111111 #
#360
b0 #
#410
b1 #
#430
b11111111 #
#440
b11111101 #
#450
b10 #
#460
b11111101 #
#470
b0 #
#480
b11 #
b11 "
#490
b1 #
#500
b1111111111111101 #
#510
b1111111111111111 #
#520
b0 #
#570
b1 #
#590
b11111111 #
#600
b11111100 #
#610
b11 #
#620
b11111100 #
#630
b0 #
#640
b100 #
b100 "
#650
b1 #
#660
b1111111111111100 #
#670
b1111111111111111 #
#680
b0 #
#730
b1 #
#750
b11111111 #
#760
b11111011 #
#770
b100 #
#780
b11111011 #
#790
b0 #
#800
b101 #
b101 "
#810
b1 #
#820
b1111111111111011 #
#830
b1111111111111111 #
#840
b0 #
#890
b1 #
#910
b11111111 #
#920
b11111010 #
#930
b101 #
#940
b11111010 #
#950
b0 #
#960
b110 #
b110 "
#970
b1 #
#980
b1111111111111010 #
#990
b1111111111111111 #
#1000
b0 #
#1050
b1 #
#1070
b11111111 #
#1080
b11111001 #
#1090
b110 #
#1100
b11111001 #
#1110
b0 #
#1120
b111 #
b111 "
#1130
b1 #
#1140
b1111111111111001 #
#1150
b1111111111111111 #
#1160
b0 #
#1210
b1 #
#1230
b11111111 #
#1240
b11111000 #
#1250
b111 #
#1260
b11111000 #
#1270
b0 #
#1280
b1000 #
b1000 "
#1290
b1 #
#1300
b1111111111111000 #
#1310
b1111111111111111 #
#1320
b0 #
#1370
b1 #
#1390
b11111111 #
#1400
b11110111 #
#1410
b1000 #
#1420
b11110111 #
#1430
b0 #
#1440
b1001 #
b1001 "
#1450
b1 #
#1460
b1111111111110111 #
#1470
b1111111111111111 #
#1480
b0 #
#1530
b1 #
#1550
b11111111 #
#1560
b11110110 #
#1570
b1001 #
#1580
b11110110 #
#1590
b0 #
#1600
b1010 #
b1010 "
#1610
b1 #
#1620
b1111111111110110 #
#1630
b1111111111111111 #
#1640
b0 #
#1690
b1 #
#1710
b11111111 #
#1720
b11110101 #
#1730
b1010 #
#1740
b11110101 #
#1750
b0 #
#1760
b1011 #
b1011 "
#1770
b1 #
#1780
b1111111111110101 #
#1790
b1111111111111111 #
#1800
b0 #
#1850
b1 #
#1870
b11111111 #
#1880
b11110100 #
#1890
b1011 #
#1900
b11110100 #
#1910
b0 #
#1920
b1100 #
b1100 "
#1930
b1 #
#1940
b1111111111110100 #
#1950
b1111111111111111 #
#1960
b0 #
#2010
b1 #
#2030
b11111111 #
#2040
b11110011 #
#2050
b1100 #
#2060
b11110011 #
#2070
b0 #
#2080
b1101 #
b1101 "
#2090
b1 #
#2100
b1111111111110011 #
#2110
b1111111111111111 #
#2120
b0 #
#2170
b1 #
#2190
b11111111 #
#2200
b11110010 #
#2210
b1101 #
#2220
b11110010 #
#2230
b0 #
#2240
b1110 #
b1110 "
#2250
b1 #
#2260
b1111111111110010 #
#2270
b1111111111111111 #
#2280
b0 #
#2330
b1 #
#2350
b11111111 #
#2360
b11110001 #
#2370
b1110 #
#2380
b11110001 #
#2390
b0 #
#2400
b1111 #
b1111 "
#2410
b1 #
#2420
b1111111111110001 #
#2430
b1111111111111111 #
#2440
b0 #
#2490
b1 #
#2510
b11111111 #
#2520
b11110000 #
#2530
b1111 #
#2540
b11110000 #
#2550
b0 #
#2560
b1 #
b0 "
b1 !
#2570
b10 #
#2580
b1 #
#2590
b0 #
#2610
b1111111111111111 #
#2620
b10 #
#2630
b0 #
#2650
b1 #
#2660
b0 #
#2670
b11111111 #
#2680
b11111110 #
#2690
b1 #
#2700
b11111110 #
#2710
b1 #
#2720
b10 #
b1 "
#2740
b0 #
#2760
b1 #
#2780
b10 #
#2790
b0 #
#2800
b1 #
#2820
b0 #
#2830
b11111110 #
#2850
b0 #
#2860
b11111111 #
#2870
b1 #
#2880
b11 #
b10 "
#2890
b10 #
#2900
b1111111111111111 #
#2910
b0 #
#2920
b10 #
#2930
b0 #
#2940
b10 #
#2950
b0 #
#2960
b1 #
#2980
b0 #
#2990
b11111111 #
#3000
b11111100 #
#3010
b11 #
#3020
b11111100 #
#3030
b1 #
#3040
b100 #
b11 "
#3050
b10 #
#3060
b1111111111111110 #
#3070
b0 #
#3080
b11 #
#3090
b0 #
#3100
b10 #
#3110
b0 #
#3120
b1 #
#3140
b0 #
#3150
b11111110 #
#3160
b11111100 #
#3170
b10 #
#3180
b11111101 #
#3190
b1 #
#3200
b101 #
b100 "
#3210
b10 #
#3220
b1111111111111101 #
#3230
b0 #
#3240
b100 #
#3250
b0 #
#3260
b10 #
#3270
b0 #
#3280
b1 #
#3300
b0 #
#3310
b11111111 #
#3320
b11111010 #
#3330
b101 #
#3340
b11111010 #
#3350
b1 #
#3360
b110 #
b101 "
#3370
b10 #
#3380
b1111111111111100 #
#3390
b0 #
#3400
b101 #
#3410
b0 #
#3420
b10 #
#3430
b0 #
#3440
b1 #
#3460
b0 #
#3470
b11111110 #
#3480
b11111010 #
#3490
b100 #
#3500
b11111011 #
#3510
b1 #
#3520
b111 #
b110 "
#3530
b10 #
#3540
b1111111111111011 #
#3550
b0 #
#3560
b110 #
#3570
b0 #
#3580
b10 #
#3590
b0 #
#3600
b1 #
#3620
b0 #
#3630
b11111111 #
#3640
b11111000 #
#3650
b111 #
#3660
b11111000 #
#3670
b1 #
#3680
b1000 #
b111 "
#3690
b10 #
#3700
b1111111111111010 #
#3710
b0 #
#3720
b111 #
#3730
b0 #
#3740
b10 #
#3750
b0 #
#3760
b1 #
#3780
b0 #
#3790
b11111110 #
#3800
b11111000 #
#3810
b110 #
#3820
b11111001 #
#3830
b1 #
#3840
b1001 #
b1000 "
#3850
b10 #
#3860
b1111111111111001 #
#3870
b0 #
#3880
b1000 #
#3890
b0 #
#3900
b10 #
#3910
b0 #
#3920
b1 #
#3940
b0 #
#3950
b11111111 #
#3960
b11110110 #
#3970
b1001 #
#3980
b11110110 #
#3990
b1 #
#4000
b1010 #
b1001 "
#4010
b10 #
#4020
b1111111111111000 #
#4030
b0 #
#4040
b1001 #
#4050
b0 #
#4060
b10 #
#4070
b0 #
#4080
b1 #
#4100
b0 #
#4110
b11111110 #
#4120
b11110110 #
#4130
b1000 #
#4140
b11110111 #
#4150
b1 #
#4160
b1011 #
b1010 "
#4170
b10 #
#4180
b1111111111110111 #
#4190
b0 #
#4200
b1010 #
#4210
b0 #
#4220
b10 #
#4230
b0 #
#4240
b1 #
#4260
b0 #
#4270
b11111111 #
#4280
b11110100 #
#4290
b1011 #
#4300
b11110100 #
#4310
b1 #
#4320
b1100 #
b1011 "
#4330
b10 #
#4340
b1111111111110110 #
#4350
b0 #
#4360
b1011 #
#4370
b0 #
#4380
b10 #
#4390
b0 #
#4400
b1 #
#4420
b0 #
#4430
b11111110 #
#4440
b11110100 #
#4450
b1010 #
#4460
b11110101 #
#4470
b1 #
#4480
b1101 #
b1100 "
#4490
b10 #
#4500
b1111111111110101 #
#4510
b0 #
#4520
b1100 #
#4530
b0 #
#4540
b10 #
#4550
b0 #
#4560
b1 #
#4580
b0 #
#4590
b11111111 #
#4600
b11110010 #
#4610
b1101 #
#4620
b11110010 #
#4630
b1 #
#4640
b1110 #
b1101 "
#4650
b10 #
#4660
b1111111111110100 #
#4670
b0 #
#4680
b1101 #
#4690
b0 #
#4700
b10 #
#4710
b0 #
#4720
b1 #
#4740
b0 #
#4750
b11111110 #
#4760
b11110010 #
#4770
b1100 #
#4780
b11110011 #
#4790
b1 #
#4800
b1111 #
b1110 "
#4810
b10 #
#4820
b1111111111110011 #
#4830
b0 #
#4840
b1110 #
#4850
b0 #
#4860
b10 #
#4870
b0 #
#4880
b1 #
#4900
b0 #
#4910
b11111111 #
#4920
b11110000 #
#4930
b1111 #
#4940
b11110000 #
#4950
b1 #
#4960
b10000 #
b1111 "
#4970
b10 #
#4980
b1111111111110010 #
#4990
b0 #
#5000
b1111 #
#5010
b0 #
#5020
b10 #
#5030
b0 #
#5040
b1 #
#5060
b0 #
#5070
b11111110 #
#5080
b11110000 #
#5090
b1110 #
#5100
b11110001 #
#5110
b1 #
#5120
b10 #
b0 "
b10 !
#5130
b11 #
#5140
b10 #
#5150
b1 #
#5160
b0 #
#5170
b1111111111111111 #
#5180
b100 #
#5190
b1 #
#5200
b0 #
#5210
b1 #
#5220
b0 #
#5230
b11111111 #
#5240
b11111101 #
#5250
b10 #
#5260
b11111101 #
#5270
b10 #
#5280
b11 #
b1 "
#5300
b1 #
#5320
b10 #
#5340
b100 #
#5350
b1 #
#5380
b0 #
#5390
b11111111 #
#5400
b11111100 #
#5410
b11 #
#5420
b11111100 #
#5430
b10 #
#5440
b100 #
b10 "
#5450
b11 #
#5460
b0 #
#5470
b1 #
#5480
b100 #
#5490
b1 #
#5500
b100 #
#5510
b1 #
#5540
b0 #
#5550
b11111101 #
#5570
b0 #
#5580
b11111111 #
#5590
b10 #
#5600
b101 #
b11 "
#5610
b11 #
#5620
b1111111111111111 #
#5630
b1 #
#5640
b110 #
#5650
b0 #
#5660
b100 #
#5670
b1 #
#5700
b0 #
#5710
b11111101 #
#5720
b11111100 #
#5730
b1 #
#5740
b11111110 #
#5750
b10 #
#5760
b110 #
b100 "
#5770
b11 #
#5780
b1111111111111110 #
#5790
b1 #
#5800
b1000 #
#5810
b0 #
#5820
b100 #
#5830
b1 #
#5860
b0 #
#5870
b11111111 #
#5880
b11111001 #
#5890
b110 #
#5900
b11111001 #
#5910
b10 #
#5920
b111 #
b101 "
#5930
b11 #
#5940
b1111111111111101 #
#5950
b1 #
#5960
b1010 #
#5970
b0 #
#5980
b100 #
#5990
b1 #
#6020
b0 #
#6030
b11111111 #
#6040
b11111000 #
#6050
b111 #
#6060
b11111000 #
#6070
b10 #
#6080
b1000 #
b110 "
#6090
b11 #
#6100
b1111111111111100 #
#6110
b1 #
#6120
b1100 #
#6130
b0 #
#6140
b100 #
#6150
b1 #
#6180
b0 #
#6190
b11111101 #
#6200
b11111001 #
#6210
b100 #
#6220
b11111011 #
#6230
b10 #
#6240
b1001 #
b111 "
#6250
b11 #
#6260
b1111111111111011 #
#6270
b1 #
#6280
b1110 #
#6290
b0 #
#6300
b100 #
#6310
b1 #
#6340
b0 #
#6350
b11111101 #
#6360
b11111000 #
#6370
b101 #
#6380
b11111010 #
#6390
b10 #
#6400
b1010 #
b1000 "
#6410
b11 #
#6420
b1111111111111010 #
#6430
b1 #
#6440
b10000 #
#6450
b0 #
#6460
b100 #
#6470
b1 #
#6500
b0 #
#6510
b11111111 #
#6520
b11110101 #
#6530
b1010 #
#6540
b11110101 #
#6550
b10 #
#6560
b1011 #
b1001 "
#6570
b11 #
#6580
b1111111111111001 #
#6590
b1 #
#6600
b10010 #
#6610
b0 #
#6620
b100 #
#6630
b1 #
#6660
b0 #
#6670
b11111111 #
#6680
b11110100 #
#6690
b1011 #
#6700
b11110100 #
#6710
b10 #
#6720
b1100 #
b1010 "
#6730
b11 #
#6740
b1111111111111000 #
#6750
b1 #
#6760
b10100 #
#6770
b0 #
#6780
b100 #
#6790
b1 #
#6820
b0 #
#6830
b11111101 #
#6840
b11110101 #
#6850
b1000 #
#6860
b11110111 #
#6870
b10 #
#6880
b1101 #
b1011 "
#6890
b11 #
#6900
b1111111111110111 #
#6910
b1 #
#6920
b10110 #
#6930
b0 #
#6940
b100 #
#6950
b1 #
#6980
b0 #
#6990
b11111101 #
#7000
b11110100 #
#7010
b1001 #
#7020
b11110110 #
#7030
b10 #
#7040
b1110 #
b1100 "
#7050
b11 #
#7060
b1111111111110110 #
#7070
b1 #
#7080
b11000 #
#7090
b0 #
#7100
b100 #
#7110
b1 #
#7140
b0 #
#7150
b11111111 #
#7160
b11110001 #
#7170
b1110 #
#7180
b11110001 #
#7190
b10 #
#7200
b1111 #
b1101 "
#7210
b11 #
#7220
b1111111111110101 #
#7230
b1 #
#7240
b11010 #
#7250
b0 #
#7260
b100 #
#7270
b1 #
#7300
b0 #
#7310
b11111111 #
#7320
b11110000 #
#7330
b1111 #
#7340
b11110000 #
#7350
b10 #
#7360
b10000 #
b1110 "
#7370
b11 #
#7380
b1111111111110100 #
#7390
b1 #
#7400
b11100 #
#7410
b0 #
#7420
b100 #
#7430
b1 #
#7460
b0 #
#7470
b11111101 #
#7480
b11110001 #
#7490
b1100 #
#7500
b11110011 #
#7510
b10 #
#7520
b10001 #
b1111 "
#7530
b11 #
#7540
b1111111111110011 #
#7550
b1 #
#7560
b11110 #
#7570
b0 #
#7580
b100 #
#7590
b1 #
#7620
b0 #
#7630
b11111101 #
#7640
b11110000 #
#7650
b1101 #
#7660
b11110010 #
#7670
b10 #
#7680
b11 #
b0 "
b11 !
#7690
b100 #
#7700
b11 #
#7710
b10 #
#7720
b0 #
#7730
b1111111111111111 #
#7740
b110 #
#7750
b1 #
#7760
b0 #
#7770
b1 #
#7780
b0 #
#7790
b11111111 #
#7800
b11111100 #
#7810
b11 #
#7820
b11111100 #
#7830
b11 #
#7840
b100 #
b1 "
#7860
b10 #
#7880
b11 #
#7900
b110 #
#7910
b1 #
#7940
b0 #
#7950
b11111110 #
#7960
b11111100 #
#7970
b10 #
#7980
b11111101 #
#7990
b11 #
#8000
b101 #
b10 "
#8010
b100 #
#8020
b1 #
#8030
b10 #
#8040
b110 #
#8050
b1 #
#8060
b110 #
#8070
b1 #
#8100
b0 #
#8110
b11111101 #
#8120
b11111100 #
#8130
b1 #
#8140
b11111110 #
#8150
b11 #
#8160
b110 #
b11 "
#8170
b100 #
#8180
b0 #
#8190
b10 #
#8200
b1001 #
#8210
b1 #
#8220
b110 #
#8230
b1 #
#8260
b0 #
#8270
b11111100 #
#8290
b0 #
#8300
b11111111 #
#8310
b11 #
#8320
b111 #
b100 "
#8330
b100 #
#8340
b1111111111111111 #
#8350
b10 #
#8360
b1100 #
#8370
b0 #
#8380
b110 #
#8390
b1 #
#8420
b0 #
#8430
b11111111 #
#8440
b11111000 #
#8450
b111 #
#8460
b11111000 #
#8470
b11 #
#8480
b1000 #
b101 "
#8490
b100 #
#8500
b1111111111111110 #
#8510
b10 #
#8520
b1111 #
#8530
b0 #
#8540
b110 #
#8550
b1 #
#8580
b0 #
#8590
b11111110 #
#8600
b11111000 #
#8610
b110 #
#8620
b11111001 #
#8630
b11 #
#8640
b1001 #
b110 "
#8650
b100 #
#8660
b1111111111111101 #
#8670
b10 #
#8680
b10010 #
#8690
b0 #
#8700
b110 #
#8710
b1 #
#8740
b0 #
#8750
b11111101 #
#8760
b11111000 #
#8770
b101 #
#8780
b11111010 #
#8790
b11 #
#8800
b1010 #
b111 "
#8810
b100 #
#8820
b1111111111111100 #
#8830
b10 #
#8840
b10101 #
#8850
b0 #
#8860
b110 #
#8870
b1 #
#8900
b0 #
#8910
b11111100 #
#8920
b11111000 #
#8930
b100 #
#8940
b11111011 #
#8950
b11 #
#8960
b1011 #
b1000 "
#8970
b100 #
#8980
b1111111111111011 #
#8990
b10 #
#9000
b11000 #
#9010
b0 #
#9020
b110 #
#9030
b1 #
#9060
b0 #
#9070
b11111111 #
#9080
b11110100 #
#9090
b1011 #
#9100
b11110100 #
#9110
b11 #
#9120
b1100 #
b1001 "
#9130
b100 #
#9140
b1111111111111010 #
#9150
b10 #
#9160
b11011 #
#9170
b0 #
#9180
b110 #
#9190
b1 #
#9220
b0 #
#9230
b11111110 #
#9240
b11110100 #
#9250
b1010 #
#9260
b11110101 #
#9270
b11 #
#9280
b1101 #
b1010 "
#9290
b100 #
#9300
b1111111111111001 #
#9310
b10 #
#9320
b11110 #
#9330
b0 #
#9340
b110 #
#9350
b1 #
#9380
b0 #
#9390
b11111101 #
#9400
b11110100 #
#9410
b1001 #
#9420
b11110110 #
#9430
b11 #
#9440
b1110 #
b1011 "
#9450
b100 #
#9460
b1111111111111000 #
#9470
b10 #
#9480
b100001 #
#9490
b0 #
#9500
b110 #
#9510
b1 #
#9540
b0 #
#9550
b11111100 #
#9560
b11110100 #
#9570
b1000 #
#9580
b11110111 #
#9590
b11 #
#9600
b1111 #
b1100 "
#9610
b100 #
#9620
b1111111111110111 #
#9630
b10 #
#9640
b100100 #
#9650
b0 #
#9660
b110 #
#9670
b1 #
#9700
b0 #
#9710
b11111111 #
#9720
b11110000 #
#9730
b1111 #
#9740
b11110000 #
#9750
b11 #
#9760
b10000 #
b1101 "
#9770
b100 #
#9780
b1111111111110110 #
#9790
b10 #
#9800
b100111 #
#9810
b0 #
#9820
b110 #
#9830
b1 #
#9860
b0 #
#9870
b11111110 #
#9880
b11110000 #
#9890
b1110 #
#9900
b11110001 #
#9910
b11 #
#9920
b10001 #
b1110 "
#9930
b100 #
#9940
b1111111111110101 #
#9950
b10 #
#9960
b101010 #
#9970
b0 #
#9980
b110 #
#9990
b1 #
#10020
b0 #
#10030
b11111101 #
#10040
b11110000 #
#10050
b1101 #
#10060
b11110010 #
#10070
b11 #
#10080
b10010 #
b1111 "
#10090
b100 #
#10100
b1111111111110100 #
#10110
b10 #
#10120
b101101 #
#10130
b0 #
#10140
b110 #
#10150
b1 #
#10180
b0 #
#10190
b11111100 #
#10200
b11110000 #
#10210
b1100 #
#10220
b11110011 #
#10230
b11 #
#10240
b100 #
b0 "
b100 !
#10250
b101 #
#10260
b100 #
#10270
b11 #
#10280
b0 #
#10290
b1111111111111111 #
#10300
b1000 #
#10310
b10 #
#10320
b0 #
#10330
b1 #
#10340
b0 #
#10350
b11111111 #
#10360
b11111011 #
#10370
b100 #
#10380
b11111011 #
#10390
b100 #
#10400
b101 #
b1 "
#10420
b11 #
#10440
b100 #
#10460
b1000 #
#10470
b10 #
#10480
b1 #
#10500
b0 #
#10510
b11111111 #
#10520
b11111010 #
#10530
b101 #
#10540
b11111010 #
#10550
b100 #
#10560
b110 #
b10 "
#10570
b101 #
#10580
b10 #
#10590
b11 #
#10600
b1000 #
#10610
b10 #
#10620
b1000 #
#10630
b10 #
#10640
b1 #
#10660
b0 #
#10670
b11111111 #
#10680
b11111001 #
#10690
b110 #
#10700
b11111001 #
#10710
b100 #
#10720
b111 #
b11 "
#10730
b101 #
#10740
b1 #
#10750
b11 #
#10760
b1100 #
#10770
b1 #
#10780
b1000 #
#10790
b10 #
#10800
b1 #
#10820
b0 #
#10830
b11111111 #
#10840
b11111000 #
#10850
b111 #
#10860
b11111000 #
#10870
b100 #
#10880
b1000 #
b100 "
#10890
b101 #
#10900
b0 #
#10910
b11 #
#10920
b10000 #
#10930
b1 #
#10940
b1000 #
#10950
b10 #
#10960
b1 #
#10980
b0 #
#10990
b11111011 #
#11010
b0 #
#11020
b11111111 #
#11030
b100 #
#11040
b1001 #
b101 "
#11050
b101 #
#11060
b1111111111111111 #
#11070
b11 #
#11080
b10100 #
#11090
b0 #
#11100
b1000 #
#11110
b10 #
#11120
b1 #
#11140
b0 #
#11150
b11111011 #
#11160
b11111010 #
#11170
b1 #
#11180
b11111110 #
#11190
b100 #
#11200
b1010 #
b110 "
#11210
b101 #
#11220
b1111111111111110 #
#11230
b11 #
#11240
b11000 #
#11250
b0 #
#11260
b1000 #
#11270
b10 #
#11280
b1 #
#11300
b0 #
#11310
b11111011 #
#11320
b11111001 #
#11330
b10 #
#11340
b11111101 #
#11350
b100 #
#11360
b1011 #
b111 "
#11370
b101 #
#11380
b1111111111111101 #
#11390
b11 #
#11400
b11100 #
#11410
b0 #
#11420
b1000 #
#11430
b10 #
#11440
b1 #
#11460
b0 #
#11470
b11111011 #
#11480
b11111000 #
#11490
b11 #
#11500
b11111100 #
#11510
b100 #
#11520
b1100 #
b1000 "
#11530
b101 #
#11540
b1111111111111100 #
#11550
b11 #
#11560
b100000 #
#11570
b0 #
#11580
b1000 #
#11590
b10 #
#11600
b1 #
#11620
b0 #
#11630
b11111111 #
#11640
b11110011 #
#11650
b1100 #
#11660
b11110011 #
#11670
b100 #
#11680
b1101 #
b1001 "
#11690
b101 #
#11700
b1111111111111011 #
#11710
b11 #
#11720
b100100 #
#11730
b0 #
#11740
b1000 #
#11750
b10 #
#11760
b1 #
#11780
b0 #
#11790
b11111111 #
#11800
b11110010 #
#11810
b1101 #
#11820
b11110010 #
#11830
b100 #
#11840
b1110 #
b1010 "
#11850
b101 #
#11860
b1111111111111010 #
#11870
b11 #
#11880
b101000 #
#11890
b0 #
#11900
b1000 #
#11910
b10 #
#11920
b1 #
#11940
b0 #
#11950
b11111111 #
#11960
b11110001 #
#11970
b1110 #
#11980
b11110001 #
#11990
b100 #
#12000
b1111 #
b1011 "
#12010
b101 #
#12020
b1111111111111001 #
#12030
b11 #
#12040
b101100 #
#12050
b0 #
#12060
b1000 #
#12070
b10 #
#12080
b1 #
#12100
b0 #
#12110
b11111111 #
#12120
b11110000 #
#12130
b1111 #
#12140
b11110000 #
#12150
b100 #
#12160
b10000 #
b1100 "
#12170
b101 #
#12180
b1111111111111000 #
#12190
b11 #
#12200
b110000 #
#12210
b0 #
#12220
b1000 #
#12230
b10 #
#12240
b1 #
#12260
b0 #
#12270
b11111011 #
#12280
b11110011 #
#12290
b1000 #
#12300
b11110111 #
#12310
b100 #
#12320
b10001 #
b1101 "
#12330
b101 #
#12340
b1111111111110111 #
#12350
b11 #
#12360
b110100 #
#12370
b0 #
#12380
b1000 #
#12390
b10 #
#12400
b1 #
#12420
b0 #
#12430
b11111011 #
#12440
b11110010 #
#12450
b1001 #
#12460
b11110110 #
#12470
b100 #
#12480
b10010 #
b1110 "
#12490
b101 #
#12500
b1111111111110110 #
#12510
b11 #
#12520
b111000 #
#12530
b0 #
#12540
b1000 #
#12550
b10 #
#12560
b1 #
#12580
b0 #
#12590
b11111011 #
#12600
b11110001 #
#12610
b1010 #
#12620
b11110101 #
#12630
b100 #
#12640
b10011 #
b1111 "
#12650
b101 #
#12660
b1111111111110101 #
#12670
b11 #
#12680
b111100 #
#12690
b0 #
#12700
b1000 #
#12710
b10 #
#12720
b1 #
#12740
b0 #
#12750
b11111011 #
#12760
b11110000 #
#12770
b1011 #
#12780
b11110100 #
#12790
b100 #
#12800
b101 #
b0 "
b101 !
#12810
b110 #
#12820
b101 #
#12830
b100 #
#12840
b0 #
#12850
b1111111111111111 #
#12860
b1010 #
#12870
b10 #
#12880
b0 #
#12890
b1 #
#12900
b0 #
#12910
b11111111 #
#12920
b11111010 #
#12930
b101 #
#12940
b11111010 #
#12950
b101 #
#12960
b110 #
b1 "
#12980
b100 #
#13000
b101 #
#13020
b1010 #
#13030
b10 #
#13040
b1 #
#13060
b0 #
#13070
b11111110 #
#13080
b11111010 #
#13090
b100 #
#13100
b11111011 #
#13110
b101 #
#13120
b111 #
b10 "
#13130
b110 #
#13140
b11 #
#13150
b100 #
#13160
b1010 #
#13170
b10 #
#13180
b1010 #
